[
    {
        "settings": {
            "version": [47, 63, 33, 13, 10],
            "hashedPassword": [6, 48, 53, 49, 13, 10],
            "password": [1, 80, 49, 2, 40, 41, 3],
            "closeCommand": [1, 66, 48, 3],
            "lst": [1, 82, 49, 2, 76, 83, 84, 48, 49, 40, 41, 3],
            "_comment": "add index of available day after 40"
        },
        "currentData": {
            "positiveA": {
                "all": [1, 82, 49, 2, 69, 84, 48, 80, 69, 40, 41, 3]
            },
            "positiveR": {
                "all": [1, 82, 49,  2, 69, 84, 48, 81, 69, 40, 41,  3]
            },
            "negativeA": {
                "all": []
            },
            "negativeR": {
                "all": [1, 82, 49,  2, 69, 84, 48, 81, 73, 40, 41,  3]
            },
            "volta": [1, 82, 49, 2, 86, 79, 76, 84, 65, 40, 41, 3],
            "voltl": [1, 82, 49, 2, 86, 79, 76, 84, 76, 40, 41, 3],
            "frequency": [1, 82, 49, 2, 70, 82, 69, 81, 85, 40, 41, 3],
            "current": [1, 82, 49, 2, 67, 85, 82, 82, 69, 40, 41, 3],
            "powp": [1, 82, 49, 2, 80, 79, 87, 80, 80, 40, 41, 3],
            "powq": [1, 82, 49, 2, 80, 79, 87, 80, 81, 40, 41, 3],
            "pows": [1, 82, 49, 2, 80, 79, 87, 69, 83, 40, 41, 3],
            "coriu": [1, 82, 49, 2, 67, 79, 82, 73, 85, 40, 41, 3],
            "coruu": [1, 82, 49, 2, 67, 79, 82, 85, 85, 40, 41, 3],
            "cosf": [1, 82, 49, 2, 67, 79, 83, 95, 102, 40, 41, 3],
            "tanf": [1, 82, 49, 2, 84, 65, 78, 95, 102, 40, 41, 3],
            "currentDate": [1, 82, 49, 2, 87, 65, 84, 67, 72, 40, 41, 3]
        },
        "archivedData": {
            "positiveA": [1, 82, 49, 2, 69, 78, 68, 80, 69, 40, 41, 3],
            "positiveR": [1, 82, 49, 2, 69, 78, 68, 81, 69, 40, 41, 3],
            "negativeA": [],
            "negativeR": [1, 82, 49, 2, 69, 78, 68, 81, 73, 40, 41, 3]
        },
        "loadProfile": {
            "profile1": [1, 82, 49, 2, 71, 82, 65, 80, 69, 40, 41, 3],
            "profile2": [1, 82, 49, 2, 71, 82, 65, 81, 69, 40, 41, 3],
            "profile3": [],
            "profile4": [1, 82, 49, 2, 71, 82, 65, 81, 73, 40, 41, 3]
        }
    }
]